{
 "generated_at": "2026-07-23 02:15",
 "alert_days": 7,
 "count": 24,
 "items": [
  {
   "id": "a0WJ200000CDbKSMA1",
   "name": "「多感覚リアリティ、感性、質感等に関する俯瞰的調査」の公募",
   "deadline": "2026-07-23",
   "days_left": 0,
   "max_amount": 0,
   "source_url": "https://www.jgrants-portal.go.jp/subsidy/a0WJ200000CDbKSMA1",
   "tag": "nationwide"
  },
  {
   "id": "a0WJ200000CDYslMAH",
   "name": "「太陽光発電導入拡大等技術開発事業／NEDOプロジェクトを核とした人材育成、産学連携等の総合的展開／ペロブスカイト太陽電池の研究開発・実装を担う人材育成特別講座」の公募",
   "deadline": "2026-07-23",
   "days_left": 0,
   "max_amount": 0,
   "source_url": "https://www.jgrants-portal.go.jp/subsidy/a0WJ200000CDYslMAH",
   "tag": "nationwide"
  },
  {
   "id": "a0WJ200000CDYiwMAH",
   "name": "①省CO2型プラスチック高度リサイクル設備導入事業（バリューチェーン）【令和７年度（補正予算）３次公募及び令和８年度２次公募】",
   "deadline": "2026-07-24",
   "days_left": 1,
   "max_amount": 7297000000,
   "source_url": "https://www.jgrants-portal.go.jp/subsidy/a0WJ200000CDYiwMAH",
   "tag": "nationwide"
  },
  {
   "id": "a0WJ200000CDYjRMAX",
   "name": "②化石資源由来プラスチックを代替する再生可能資源由来素材 の省CO2型製造設備導入事業（バリューチェーン）【令和７年度（補正予算）第３次公募及び令和８年度第２次公募】",
   "deadline": "2026-07-24",
   "days_left": 1,
   "max_amount": 7297000000,
   "source_url": "https://www.jgrants-portal.go.jp/subsidy/a0WJ200000CDYjRMAX",
   "tag": "nationwide"
  },
  {
   "id": "a0WJ200000CDYkCMAX",
   "name": "③太陽光パネルリサイクル設備導入事業（バリューチェーン）【令和７年度（補正予算）第３次公募及び令和８年度第２次公募】",
   "deadline": "2026-07-24",
   "days_left": 1,
   "max_amount": 7297000000,
   "source_url": "https://www.jgrants-portal.go.jp/subsidy/a0WJ200000CDYkCMAX",
   "tag": "nationwide"
  },
  {
   "id": "a0WJ200000CDYkHMAX",
   "name": "④リチウム蓄電池リサイクル設備導入事業（バリューチェーン）【令和７年度（補正予算）第３次公募及び令和８年度第２次公募】",
   "deadline": "2026-07-24",
   "days_left": 1,
   "max_amount": 7297000000,
   "source_url": "https://www.jgrants-portal.go.jp/subsidy/a0WJ200000CDYkHMAX",
   "tag": "nationwide"
  },
  {
   "id": "a0WJ200000CDYk0MAH",
   "name": "⑤金属破砕・選別設備導入事業（バリューチェーン）【令和７年度（補正予算）第３次公募及び第８年度第２次公募】",
   "deadline": "2026-07-24",
   "days_left": 1,
   "max_amount": 7297000000,
   "source_url": "https://www.jgrants-portal.go.jp/subsidy/a0WJ200000CDYk0MAH",
   "tag": "nationwide"
  },
  {
   "id": "a0WJ200000CDbyeMAD",
   "name": "「経済安全保障重要技術育成プログラム／ハイブリッドクラウド利用基盤技術の開発／不正機能排除技術の社会実装に向けた市場・技術動向等に係る調査」の公募",
   "deadline": "2026-07-24",
   "days_left": 1,
   "max_amount": 0,
   "source_url": "https://www.jgrants-portal.go.jp/subsidy/a0WJ200000CDbyeMAD",
   "tag": "nationwide"
  },
  {
   "id": "a0WJ200000CDapWMAT",
   "name": "【令和８年度】先進的な資源循環投資促進事業",
   "deadline": "2026-07-24",
   "days_left": 1,
   "max_amount": 36500000000,
   "source_url": "https://www.jgrants-portal.go.jp/subsidy/a0WJ200000CDapWMAT",
   "tag": "okinawa"
  },
  {
   "id": "a0WJ200000CDbzXMAT",
   "name": "【農林水産省】令和7年度補正ウクライナ農業回復緊急支援事業（２次公募）",
   "deadline": "2026-07-24",
   "days_left": 1,
   "max_amount": 0,
   "source_url": "https://www.jgrants-portal.go.jp/subsidy/a0WJ200000CDbzXMAT",
   "tag": "nationwide"
  },
  {
   "id": "a0WJ200000CDapkMAD",
   "name": "中小企業生産性革命推進事業_事業承継・M&A補助金(15次公募)_PMI推進枠(PMI専門家活用類型)",
   "deadline": "2026-07-24",
   "days_left": 1,
   "max_amount": 1500000,
   "source_url": "https://www.jgrants-portal.go.jp/subsidy/a0WJ200000CDapkMAD",
   "tag": "shokei"
  },
  {
   "id": "a0WJ200000CDaplMAD",
   "name": "中小企業生産性革命推進事業_事業承継・M&A補助金(15次公募)_PMI推進枠(事業統合投資類型)",
   "deadline": "2026-07-24",
   "days_left": 1,
   "max_amount": 10000000,
   "source_url": "https://www.jgrants-portal.go.jp/subsidy/a0WJ200000CDaplMAD",
   "tag": "shokei"
  },
  {
   "id": "a0WJ200000CDapgMAD",
   "name": "中小企業生産性革命推進事業_事業承継・M&A補助金(15次公募)_事業承継促進枠",
   "deadline": "2026-07-24",
   "days_left": 1,
   "max_amount": 10000000,
   "source_url": "https://www.jgrants-portal.go.jp/subsidy/a0WJ200000CDapgMAD",
   "tag": "shokei"
  },
  {
   "id": "a0WJ200000CDapmMAD",
   "name": "中小企業生産性革命推進事業_事業承継・M&A補助金(15次公募)_専門家活用枠(小規模売り手支援類型)",
   "deadline": "2026-07-24",
   "days_left": 1,
   "max_amount": 4500000,
   "source_url": "https://www.jgrants-portal.go.jp/subsidy/a0WJ200000CDapmMAD",
   "tag": "shokei"
  },
  {
   "id": "a0WJ200000CDapjMAD",
   "name": "中小企業生産性革命推進事業_事業承継・M&A補助金(15次公募)_専門家活用枠(買い手支援類型-100億企業特例)",
   "deadline": "2026-07-24",
   "days_left": 1,
   "max_amount": 20000000,
   "source_url": "https://www.jgrants-portal.go.jp/subsidy/a0WJ200000CDapjMAD",
   "tag": "shokei"
  },
  {
   "id": "a0WJ200000CDapiMAD",
   "name": "中小企業生産性革命推進事業_事業承継・M&A補助金(15次公募)_専門家活用枠(買い手支援類型／売り手支援類型)",
   "deadline": "2026-07-24",
   "days_left": 1,
   "max_amount": 8000000,
   "source_url": "https://www.jgrants-portal.go.jp/subsidy/a0WJ200000CDapiMAD",
   "tag": "shokei"
  },
  {
   "id": "a0WJ200000CDaphMAD",
   "name": "中小企業生産性革命推進事業_事業承継・M&A補助金(15次公募)_廃業・再チャレンジ枠",
   "deadline": "2026-07-24",
   "days_left": 1,
   "max_amount": 3000000,
   "source_url": "https://www.jgrants-portal.go.jp/subsidy/a0WJ200000CDaphMAD",
   "tag": "shokei"
  },
  {
   "id": "a0WJ200000CDYqvMAH",
   "name": "令和８年度　ＦＳ調査事業　第２次公募　【　廃棄物処理施設を核とした地域循環共生圏構築促進事業　】",
   "deadline": "2026-07-24",
   "days_left": 1,
   "max_amount": 0,
   "source_url": "https://www.jgrants-portal.go.jp/subsidy/a0WJ200000CDYqvMAH",
   "tag": "nationwide"
  },
  {
   "id": "a0WJ200000CDYjqMAH",
   "name": "「経済安全保障重要技術育成プログラム／高効率・高品質レーザー加工技術の開発／研究開発項目③高品質・高出力な半導体レーザーの研究開発及び当該半導体レーザーを用いた車載用LiDARの構築」の公募",
   "deadline": "2026-07-27",
   "days_left": 4,
   "max_amount": 0,
   "source_url": "https://www.jgrants-portal.go.jp/subsidy/a0WJ200000CDYjqMAH",
   "tag": "nationwide"
  },
  {
   "id": "a0WJ200000CDbJKMA1",
   "name": "【応募事業者】令和８年度 プラスチック等資源循環システム構築実証事業　＜二次公募＞",
   "deadline": "2026-07-27",
   "days_left": 4,
   "max_amount": 0,
   "source_url": "https://www.jgrants-portal.go.jp/subsidy/a0WJ200000CDbJKMA1",
   "tag": "okinawa"
  },
  {
   "id": "a0WJ200000CDbonMAD",
   "name": "「インフラ管理DXにおける地下埋設物データ整備手法活用の人材育成講座のあり方に関する調査」の公募",
   "deadline": "2026-07-28",
   "days_left": 5,
   "max_amount": 0,
   "source_url": "https://www.jgrants-portal.go.jp/subsidy/a0WJ200000CDbonMAD",
   "tag": "nationwide"
  },
  {
   "id": "naha_city-1007180",
   "name": "令和8年度 那覇市人手不足対応支援補助金",
   "deadline": "2026-07-28",
   "days_left": 5,
   "max_amount": null,
   "source_url": "https://www.city.naha.okinawa.jp/business/kigyouricchi/1003642/1007180.html",
   "tag": "okinawa"
  },
  {
   "id": "a0WJ200000CDc0JMAT",
   "name": "「スタートアップに対する経営管理・事業化支援人材の伴走支援モデルに係る調査事業」の公募",
   "deadline": "2026-07-30",
   "days_left": 7,
   "max_amount": 0,
   "source_url": "https://www.jgrants-portal.go.jp/subsidy/a0WJ200000CDc0JMAT",
   "tag": "nationwide"
  },
  {
   "id": "a0WJ200000CDKZFMA5",
   "name": "令和８年度_グリーンスローモビリティ等導入促進事業",
   "deadline": "2026-07-30",
   "days_left": 7,
   "max_amount": 0,
   "source_url": "https://www.jgrants-portal.go.jp/subsidy/a0WJ200000CDKZFMA5",
   "tag": "nationwide"
  }
 ]
}